{
    "available_space": false,
    "content": [
        {
            "id": "75bwpAlX-Js",
            "name": "LOS HERMANOS VEGA - EL RAYO DE SINALOA.wmv-75bwpAlX-Js.mp4",
            "path": "/home/alanmatzumiya/Videos/container/l1/videos/LOS HERMANOS VEGA - EL RAYO DE SINALOA.wmv-75bwpAlX-Js.mp4",
            "size": 6.804889999999999,
            "url": "https://github.com/circuitalmynds/music_l1/raw/main/videos/LOS HERMANOS VEGA - EL RAYO DE SINALOA.wmv-75bwpAlX-Js.mp4"
        },
        {
            "id": "BmXZDGU4riY",
            "name": "Lil Rob- I'm Coming Home FT. Aki Star-BmXZDGU4riY.mp4",
            "path": "/home/alanmatzumiya/Videos/container/l1/videos/Lil Rob- I'm Coming Home FT. Aki Star-BmXZDGU4riY.mp4",
            "size": 5.942251,
            "url": "https://github.com/circuitalmynds/music_l1/raw/main/videos/Lil Rob- I'm Coming Home FT. Aki Star-BmXZDGU4riY.mp4"
        },
        {
            "id": "vFhVYEcB1Gg",
            "name": "Liga Desorden - Soldado-vFhVYEcB1Gg.mp4",
            "path": "/home/alanmatzumiya/Videos/container/l1/videos/Liga Desorden - Soldado-vFhVYEcB1Gg.mp4",
            "size": 2.507555,
            "url": "https://github.com/circuitalmynds/music_l1/raw/main/videos/Liga Desorden - Soldado-vFhVYEcB1Gg.mp4"
        },
        {
            "id": "y7X-tYMpQVw",
            "name": "Lloyd Green - Show Me The Way To The Circus-y7X-tYMpQVw.mp4",
            "path": "/home/alanmatzumiya/Videos/container/l1/videos/Lloyd Green - Show Me The Way To The Circus-y7X-tYMpQVw.mp4",
            "size": 8.10417,
            "url": "https://github.com/circuitalmynds/music_l1/raw/main/videos/Lloyd Green - Show Me The Way To The Circus-y7X-tYMpQVw.mp4"
        },
        {
            "id": "RrwjYOs7q0M",
            "name": "Leonardo Favio - Fuiste M\u00eda Un Verano-RrwjYOs7q0M.mp4",
            "path": "/home/alanmatzumiya/Videos/container/l1/videos/Leonardo Favio - Fuiste M\u00eda Un Verano-RrwjYOs7q0M.mp4",
            "size": 8.344419,
            "url": "https://github.com/circuitalmynds/music_l1/raw/main/videos/Leonardo Favio - Fuiste M\u00eda Un Verano-RrwjYOs7q0M.mp4"
        },
        {
            "id": "Csr5er3NHCY",
            "name": "Lele Pons & Yandel - Bubble Gum (Official Music Video)-Csr5er3NHCY.mp4",
            "path": "/home/alanmatzumiya/Videos/container/l1/videos/Lele Pons & Yandel - Bubble Gum (Official Music Video)-Csr5er3NHCY.mp4",
            "size": 12.827717999999999,
            "url": "https://github.com/circuitalmynds/music_l1/raw/main/videos/Lele Pons & Yandel - Bubble Gum (Official Music Video)-Csr5er3NHCY.mp4"
        },
        {
            "id": "nNEb2k_EmMg",
            "name": "Laura Branigan - Gloria (Official Music Video)-nNEb2k_EmMg.mp4",
            "path": "/home/alanmatzumiya/Videos/container/l1/videos/Laura Branigan - Gloria (Official Music Video)-nNEb2k_EmMg.mp4",
            "size": 15.306427,
            "url": "https://github.com/circuitalmynds/music_l1/raw/main/videos/Laura Branigan - Gloria (Official Music Video)-nNEb2k_EmMg.mp4"
        },
        {
            "id": "pgBBR3_tnao",
            "name": "Liga Desorden - Extra\u00f1o-pgBBR3_tnao.mp4",
            "path": "/home/alanmatzumiya/Videos/container/l1/videos/Liga Desorden - Extra\u00f1o-pgBBR3_tnao.mp4",
            "size": 3.613132,
            "url": "https://github.com/circuitalmynds/music_l1/raw/main/videos/Liga Desorden - Extra\u00f1o-pgBBR3_tnao.mp4"
        },
        {
            "id": "31lJEjh-JTI",
            "name": "L.O.V.E. Love-31lJEjh-JTI.mp4",
            "path": "/home/alanmatzumiya/Videos/container/l1/videos/L.O.V.E. Love-31lJEjh-JTI.mp4",
            "size": 3.939888,
            "url": "https://github.com/circuitalmynds/music_l1/raw/main/videos/L.O.V.E. Love-31lJEjh-JTI.mp4"
        },
        {
            "id": "Hw2ol8XNE_Q",
            "name": "Los Hermanos Vega La Vibora Peligrosa-Hw2ol8XNE_Q.mp4",
            "path": "/home/alanmatzumiya/Videos/container/l1/videos/Los Hermanos Vega La Vibora Peligrosa-Hw2ol8XNE_Q.mp4",
            "size": 5.879993,
            "url": "https://github.com/circuitalmynds/music_l1/raw/main/videos/Los Hermanos Vega La Vibora Peligrosa-Hw2ol8XNE_Q.mp4"
        },
        {
            "id": "yJqJ4vBSR2Y",
            "name": "Lil Rob - Fork In The Road (NEW 2010) Exclusive-yJqJ4vBSR2Y.mp4",
            "path": "/home/alanmatzumiya/Videos/container/l1/videos/Lil Rob - Fork In The Road (NEW 2010) Exclusive-yJqJ4vBSR2Y.mp4",
            "size": 6.1489519999999995,
            "url": "https://github.com/circuitalmynds/music_l1/raw/main/videos/Lil Rob - Fork In The Road (NEW 2010) Exclusive-yJqJ4vBSR2Y.mp4"
        },
        {
            "id": "uCAgQp1STS4",
            "name": "Los Invasores Necesito Verte-uCAgQp1STS4.mp4",
            "path": "/home/alanmatzumiya/Videos/container/l1/videos/Los Invasores Necesito Verte-uCAgQp1STS4.mp4",
            "size": 3.548593,
            "url": "https://github.com/circuitalmynds/music_l1/raw/main/videos/Los Invasores Necesito Verte-uCAgQp1STS4.mp4"
        },
        {
            "id": "d5iBk3wgLNc",
            "name": "Limp Bizkit - Phat Groove-d5iBk3wgLNc.mp4",
            "path": "/home/alanmatzumiya/Videos/container/l1/videos/Limp Bizkit - Phat Groove-d5iBk3wgLNc.mp4",
            "size": 1.531958,
            "url": "https://github.com/circuitalmynds/music_l1/raw/main/videos/Limp Bizkit - Phat Groove-d5iBk3wgLNc.mp4"
        },
        {
            "id": "-T7kzvqI_vs",
            "name": "La Ment--T7kzvqI_vs.mp4",
            "path": "/home/alanmatzumiya/Videos/container/l1/videos/La Ment--T7kzvqI_vs.mp4",
            "size": 5.6303719999999995,
            "url": "https://github.com/circuitalmynds/music_l1/raw/main/videos/La Ment--T7kzvqI_vs.mp4"
        },
        {
            "id": "xo6IPQxerNA",
            "name": "los herederos de nuevo leon tu dices cuando-xo6IPQxerNA.mp4",
            "path": "/home/alanmatzumiya/Videos/container/l1/videos/los herederos de nuevo leon tu dices cuando-xo6IPQxerNA.mp4",
            "size": 4.011134,
            "url": "https://github.com/circuitalmynds/music_l1/raw/main/videos/los herederos de nuevo leon tu dices cuando-xo6IPQxerNA.mp4"
        },
        {
            "id": "nJ6CG9XiKfA",
            "name": "La que sea Los Herederos de Nuevo Le\u00f3n-nJ6CG9XiKfA.mp4",
            "path": "/home/alanmatzumiya/Videos/container/l1/videos/La que sea Los Herederos de Nuevo Le\u00f3n-nJ6CG9XiKfA.mp4",
            "size": 4.81086,
            "url": "https://github.com/circuitalmynds/music_l1/raw/main/videos/La que sea Los Herederos de Nuevo Le\u00f3n-nJ6CG9XiKfA.mp4"
        },
        {
            "id": "1JsoE3BzK1A",
            "name": "Los Hermanos Vega Florita Del Alma-1JsoE3BzK1A.mp4",
            "path": "/home/alanmatzumiya/Videos/container/l1/videos/Los Hermanos Vega Florita Del Alma-1JsoE3BzK1A.mp4",
            "size": 4.819941,
            "url": "https://github.com/circuitalmynds/music_l1/raw/main/videos/Los Hermanos Vega Florita Del Alma-1JsoE3BzK1A.mp4"
        },
        {
            "id": "UPUa8foTDcg",
            "name": "La Polla Records - Y Ahora Que (EP completo)-UPUa8foTDcg.mp4",
            "path": "/home/alanmatzumiya/Videos/container/l1/videos/La Polla Records - Y Ahora Que (EP completo)-UPUa8foTDcg.mp4",
            "size": 49.340520999999995,
            "url": "https://github.com/circuitalmynds/music_l1/raw/main/videos/La Polla Records - Y Ahora Que (EP completo)-UPUa8foTDcg.mp4"
        },
        {
            "id": "bnZ-Ub2Ny_A",
            "name": "Los Hermanos Vega Amigo Tabernero-bnZ-Ub2Ny_A.mp4",
            "path": "/home/alanmatzumiya/Videos/container/l1/videos/Los Hermanos Vega Amigo Tabernero-bnZ-Ub2Ny_A.mp4",
            "size": 6.781167,
            "url": "https://github.com/circuitalmynds/music_l1/raw/main/videos/Los Hermanos Vega Amigo Tabernero-bnZ-Ub2Ny_A.mp4"
        },
        {
            "id": "y9y5DnZQDvM",
            "name": "LOS INVASORES DE NUEVO LE\u00d3N - Voy A Quemar El Colch\u00f3n-y9y5DnZQDvM.mp4",
            "path": "/home/alanmatzumiya/Videos/container/l1/videos/LOS INVASORES DE NUEVO LE\u00d3N - Voy A Quemar El Colch\u00f3n-y9y5DnZQDvM.mp4",
            "size": 7.812918,
            "url": "https://github.com/circuitalmynds/music_l1/raw/main/videos/LOS INVASORES DE NUEVO LE\u00d3N - Voy A Quemar El Colch\u00f3n-y9y5DnZQDvM.mp4"
        },
        {
            "id": "W-sQFm85QHY",
            "name": "Los Cadetes de Linares - Ven a Buscarme-W-sQFm85QHY.mp4",
            "path": "/home/alanmatzumiya/Videos/container/l1/videos/Los Cadetes de Linares - Ven a Buscarme-W-sQFm85QHY.mp4",
            "size": 2.705778,
            "url": "https://github.com/circuitalmynds/music_l1/raw/main/videos/Los Cadetes de Linares - Ven a Buscarme-W-sQFm85QHY.mp4"
        },
        {
            "id": "J81CS9KiuZo",
            "name": "LIT killah - Si Te Vas (Official Video)-J81CS9KiuZo.mp4",
            "path": "/home/alanmatzumiya/Videos/container/l1/videos/LIT killah - Si Te Vas (Official Video)-J81CS9KiuZo.mp4",
            "size": 14.782019,
            "url": "https://github.com/circuitalmynds/music_l1/raw/main/videos/LIT killah - Si Te Vas (Official Video)-J81CS9KiuZo.mp4"
        },
        {
            "id": "jj4_E0aoRZQ",
            "name": "Liga Desorden - Skafandra-jj4_E0aoRZQ.mp4",
            "path": "/home/alanmatzumiya/Videos/container/l1/videos/Liga Desorden - Skafandra-jj4_E0aoRZQ.mp4",
            "size": 2.424093,
            "url": "https://github.com/circuitalmynds/music_l1/raw/main/videos/Liga Desorden - Skafandra-jj4_E0aoRZQ.mp4"
        },
        {
            "id": "f6LT6GU9nBo",
            "name": "los herederos de nuevo leon para ti mi amor-f6LT6GU9nBo.mp4",
            "path": "/home/alanmatzumiya/Videos/container/l1/videos/los herederos de nuevo leon para ti mi amor-f6LT6GU9nBo.mp4",
            "size": 5.4133759999999995,
            "url": "https://github.com/circuitalmynds/music_l1/raw/main/videos/los herederos de nuevo leon para ti mi amor-f6LT6GU9nBo.mp4"
        },
        {
            "id": "bIn9dKqNWAU",
            "name": "Lil Rob - Gangster Gangster 'Rough_with Lyrics' (NEW 2010) CRM Exclusive-bIn9dKqNWAU.mp4",
            "path": "/home/alanmatzumiya/Videos/container/l1/videos/Lil Rob - Gangster Gangster 'Rough_with Lyrics' (NEW 2010) CRM Exclusive-bIn9dKqNWAU.mp4",
            "size": 10.998928,
            "url": "https://github.com/circuitalmynds/music_l1/raw/main/videos/Lil Rob - Gangster Gangster 'Rough_with Lyrics' (NEW 2010) CRM Exclusive-bIn9dKqNWAU.mp4"
        },
        {
            "id": "Dn8vzTsnPps",
            "name": "Limp Bizkit - My Way-Dn8vzTsnPps.mp4",
            "path": "/home/alanmatzumiya/Videos/container/l1/videos/Limp Bizkit - My Way-Dn8vzTsnPps.mp4",
            "size": 16.282994,
            "url": "https://github.com/circuitalmynds/music_l1/raw/main/videos/Limp Bizkit - My Way-Dn8vzTsnPps.mp4"
        },
        {
            "id": "V9DdNSevc6o",
            "name": "los herederos de nuevo leon - sin alas-V9DdNSevc6o.mp4",
            "path": "/home/alanmatzumiya/Videos/container/l1/videos/los herederos de nuevo leon - sin alas-V9DdNSevc6o.mp4",
            "size": 7.510583,
            "url": "https://github.com/circuitalmynds/music_l1/raw/main/videos/los herederos de nuevo leon - sin alas-V9DdNSevc6o.mp4"
        },
        {
            "id": "qUlyPiDN7kg",
            "name": "La Arrolladora Banda El Lim\u00f3n De Ren\u00e9 Camacho - Si Yo Te Contara (Lyric Video)-qUlyPiDN7kg.mp4",
            "path": "/home/alanmatzumiya/Videos/container/l1/videos/La Arrolladora Banda El Lim\u00f3n De Ren\u00e9 Camacho - Si Yo Te Contara (Lyric Video)-qUlyPiDN7kg.mp4",
            "size": 4.3959909999999995,
            "url": "https://github.com/circuitalmynds/music_l1/raw/main/videos/La Arrolladora Banda El Lim\u00f3n De Ren\u00e9 Camacho - Si Yo Te Contara (Lyric Video)-qUlyPiDN7kg.mp4"
        },
        {
            "id": "onZyNJTfBdU",
            "name": "Los Hermanos Vega Ya Tengo Amor-onZyNJTfBdU.mp4",
            "path": "/home/alanmatzumiya/Videos/container/l1/videos/Los Hermanos Vega Ya Tengo Amor-onZyNJTfBdU.mp4",
            "size": 6.551735,
            "url": "https://github.com/circuitalmynds/music_l1/raw/main/videos/Los Hermanos Vega Ya Tengo Amor-onZyNJTfBdU.mp4"
        },
        {
            "id": "Pd7O3U24cog",
            "name": "LEO DAN - Tu  (RANCHERA)-Pd7O3U24cog.mp4",
            "path": "/home/alanmatzumiya/Videos/container/l1/videos/LEO DAN - Tu  (RANCHERA)-Pd7O3U24cog.mp4",
            "size": 6.661963,
            "url": "https://github.com/circuitalmynds/music_l1/raw/main/videos/LEO DAN - Tu  (RANCHERA)-Pd7O3U24cog.mp4"
        },
        {
            "id": "2YC0tK93FIk",
            "name": "Los Tres en Cajuelados-2YC0tK93FIk.mp4",
            "path": "/home/alanmatzumiya/Videos/container/l1/videos/Los Tres en Cajuelados-2YC0tK93FIk.mp4",
            "size": 5.33963,
            "url": "https://github.com/circuitalmynds/music_l1/raw/main/videos/Los Tres en Cajuelados-2YC0tK93FIk.mp4"
        },
        {
            "id": "nezPh0cvKVs",
            "name": "LOS CADETES DE LINARES MI CORRIDO-nezPh0cvKVs.mp4",
            "path": "/home/alanmatzumiya/Videos/container/l1/videos/LOS CADETES DE LINARES MI CORRIDO-nezPh0cvKVs.mp4",
            "size": 3.630801,
            "url": "https://github.com/circuitalmynds/music_l1/raw/main/videos/LOS CADETES DE LINARES MI CORRIDO-nezPh0cvKVs.mp4"
        },
        {
            "id": "OzVAWOy-27s",
            "name": "Like A Baby ~ Toni Arden  (1957)-OzVAWOy-27s.mp4",
            "path": "/home/alanmatzumiya/Videos/container/l1/videos/Like A Baby ~ Toni Arden  (1957)-OzVAWOy-27s.mp4",
            "size": 7.11663,
            "url": "https://github.com/circuitalmynds/music_l1/raw/main/videos/Like A Baby ~ Toni Arden  (1957)-OzVAWOy-27s.mp4"
        },
        {
            "id": "V0g4eB8FVkg",
            "name": "Leo Dan - La Ni\u00f1a Est\u00e1 Triste (En Vivo) ft. Jes\u00fas 'Tuti' Mart\u00ednez-V0g4eB8FVkg.mp4",
            "path": "/home/alanmatzumiya/Videos/container/l1/videos/Leo Dan - La Ni\u00f1a Est\u00e1 Triste (En Vivo) ft. Jes\u00fas 'Tuti' Mart\u00ednez-V0g4eB8FVkg.mp4",
            "size": 15.899928999999998,
            "url": "https://github.com/circuitalmynds/music_l1/raw/main/videos/Leo Dan - La Ni\u00f1a Est\u00e1 Triste (En Vivo) ft. Jes\u00fas 'Tuti' Mart\u00ednez-V0g4eB8FVkg.mp4"
        },
        {
            "id": "t_7t5vCYQ1c",
            "name": "Leonardo Favio QUIERO APRENDER DE MEMORIA-t_7t5vCYQ1c.mp4",
            "path": "/home/alanmatzumiya/Videos/container/l1/videos/Leonardo Favio QUIERO APRENDER DE MEMORIA-t_7t5vCYQ1c.mp4",
            "size": 9.10655,
            "url": "https://github.com/circuitalmynds/music_l1/raw/main/videos/Leonardo Favio QUIERO APRENDER DE MEMORIA-t_7t5vCYQ1c.mp4"
        },
        {
            "id": "JTMVOzPPtiw",
            "name": "Limp Bizkit - Nookie (Official Music Video)-JTMVOzPPtiw.mp4",
            "path": "/home/alanmatzumiya/Videos/container/l1/videos/Limp Bizkit - Nookie (Official Music Video)-JTMVOzPPtiw.mp4",
            "size": 19.215721,
            "url": "https://github.com/circuitalmynds/music_l1/raw/main/videos/Limp Bizkit - Nookie (Official Music Video)-JTMVOzPPtiw.mp4"
        },
        {
            "id": "9BsC4fq8c9o",
            "name": "Lonesome Train (on a lonesome track) - Johnny Burnette's Rock 'n' Roll Trio-9BsC4fq8c9o.mp4",
            "path": "/home/alanmatzumiya/Videos/container/l1/videos/Lonesome Train (on a lonesome track) - Johnny Burnette's Rock 'n' Roll Trio-9BsC4fq8c9o.mp4",
            "size": 8.716845,
            "url": "https://github.com/circuitalmynds/music_l1/raw/main/videos/Lonesome Train (on a lonesome track) - Johnny Burnette's Rock 'n' Roll Trio-9BsC4fq8c9o.mp4"
        },
        {
            "id": "1QMY8dQhhiM",
            "name": "LUIS ANGEL  LLORARAS-1QMY8dQhhiM.mp4",
            "path": "/home/alanmatzumiya/Videos/container/l1/videos/LUIS ANGEL  LLORARAS-1QMY8dQhhiM.mp4",
            "size": 5.265808,
            "url": "https://github.com/circuitalmynds/music_l1/raw/main/videos/LUIS ANGEL  LLORARAS-1QMY8dQhhiM.mp4"
        },
        {
            "id": "4QVUmRjFRNA",
            "name": "Los Hermanos Vega Pirulino-4QVUmRjFRNA.mp4",
            "path": "/home/alanmatzumiya/Videos/container/l1/videos/Los Hermanos Vega Pirulino-4QVUmRjFRNA.mp4",
            "size": 7.420464,
            "url": "https://github.com/circuitalmynds/music_l1/raw/main/videos/Los Hermanos Vega Pirulino-4QVUmRjFRNA.mp4"
        },
        {
            "id": "ur5Q0XUbK38",
            "name": "Limp Bizkit-Jane Says-ur5Q0XUbK38.mp4",
            "path": "/home/alanmatzumiya/Videos/container/l1/videos/Limp Bizkit-Jane Says-ur5Q0XUbK38.mp4",
            "size": 4.497723,
            "url": "https://github.com/circuitalmynds/music_l1/raw/main/videos/Limp Bizkit-Jane Says-ur5Q0XUbK38.mp4"
        },
        {
            "id": "ClXUlSx65y4",
            "name": "Laid Back - Don't Shoot The Sun Down (Iive)-ClXUlSx65y4.mp4",
            "path": "/home/alanmatzumiya/Videos/container/l1/videos/Laid Back - Don't Shoot The Sun Down (Iive)-ClXUlSx65y4.mp4",
            "size": 12.889699,
            "url": "https://github.com/circuitalmynds/music_l1/raw/main/videos/Laid Back - Don't Shoot The Sun Down (Iive)-ClXUlSx65y4.mp4"
        },
        {
            "id": "TcU57tAKzng",
            "name": "Lenny Kravitz - Let Love Rule (Official Music Video)-TcU57tAKzng.mp4",
            "path": "/home/alanmatzumiya/Videos/container/l1/videos/Lenny Kravitz - Let Love Rule (Official Music Video)-TcU57tAKzng.mp4",
            "size": 22.818497,
            "url": "https://github.com/circuitalmynds/music_l1/raw/main/videos/Lenny Kravitz - Let Love Rule (Official Music Video)-TcU57tAKzng.mp4"
        },
        {
            "id": "hRl5e5rX82g",
            "name": "Los Invasores de Nuevo Leon - Ay mi madre-hRl5e5rX82g.mp4",
            "path": "/home/alanmatzumiya/Videos/container/l1/videos/Los Invasores de Nuevo Leon - Ay mi madre-hRl5e5rX82g.mp4",
            "size": 7.558755,
            "url": "https://github.com/circuitalmynds/music_l1/raw/main/videos/Los Invasores de Nuevo Leon - Ay mi madre-hRl5e5rX82g.mp4"
        },
        {
            "id": "7ECx2DyPqR0",
            "name": "Los Herederos de Nuevo Le\u00f3n - Es Mejor Decir Adi\u00f3s ( Audio Oficial )-7ECx2DyPqR0.mp4",
            "path": "/home/alanmatzumiya/Videos/container/l1/videos/Los Herederos de Nuevo Le\u00f3n - Es Mejor Decir Adi\u00f3s ( Audio Oficial )-7ECx2DyPqR0.mp4",
            "size": 7.9722,
            "url": "https://github.com/circuitalmynds/music_l1/raw/main/videos/Los Herederos de Nuevo Le\u00f3n - Es Mejor Decir Adi\u00f3s ( Audio Oficial )-7ECx2DyPqR0.mp4"
        },
        {
            "id": "F22wf_UWumM",
            "name": "La Arrolladora Banda El Lim\u00f3n De Ren\u00e9 Camacho - M\u00e1s Adelante (Closed-Captioned)-F22wf_UWumM.mp4",
            "path": "/home/alanmatzumiya/Videos/container/l1/videos/La Arrolladora Banda El Lim\u00f3n De Ren\u00e9 Camacho - M\u00e1s Adelante (Closed-Captioned)-F22wf_UWumM.mp4",
            "size": 11.479607999999999,
            "url": "https://github.com/circuitalmynds/music_l1/raw/main/videos/La Arrolladora Banda El Lim\u00f3n De Ren\u00e9 Camacho - M\u00e1s Adelante (Closed-Captioned)-F22wf_UWumM.mp4"
        },
        {
            "id": "szFP_NalqCE",
            "name": "La Polla Records - Y ahora que-szFP_NalqCE.mp4",
            "path": "/home/alanmatzumiya/Videos/container/l1/videos/La Polla Records - Y ahora que-szFP_NalqCE.mp4",
            "size": 2.631687,
            "url": "https://github.com/circuitalmynds/music_l1/raw/main/videos/La Polla Records - Y ahora que-szFP_NalqCE.mp4"
        },
        {
            "id": "WkCEPiuK5cM",
            "name": "Las cruces-WkCEPiuK5cM.mp4",
            "path": "/home/alanmatzumiya/Videos/container/l1/videos/Las cruces-WkCEPiuK5cM.mp4",
            "size": 8.514536,
            "url": "https://github.com/circuitalmynds/music_l1/raw/main/videos/Las cruces-WkCEPiuK5cM.mp4"
        },
        {
            "id": "5yUP0LUepxU",
            "name": "Los Herederos de Nuevo Le\u00f3n - Te Prometo Que Vuelvo ( Audio Oficial )-5yUP0LUepxU.mp4",
            "path": "/home/alanmatzumiya/Videos/container/l1/videos/Los Herederos de Nuevo Le\u00f3n - Te Prometo Que Vuelvo ( Audio Oficial )-5yUP0LUepxU.mp4",
            "size": 7.645778999999999,
            "url": "https://github.com/circuitalmynds/music_l1/raw/main/videos/Los Herederos de Nuevo Le\u00f3n - Te Prometo Que Vuelvo ( Audio Oficial )-5yUP0LUepxU.mp4"
        },
        {
            "id": "x7orq2Gjls8",
            "name": "Los Herederos de Nuevo Leon - Nac\u00ed Para Quererla ( Audio Oficial )-x7orq2Gjls8.mp4",
            "path": "/home/alanmatzumiya/Videos/container/l1/videos/Los Herederos de Nuevo Leon - Nac\u00ed Para Quererla ( Audio Oficial )-x7orq2Gjls8.mp4",
            "size": 7.840132,
            "url": "https://github.com/circuitalmynds/music_l1/raw/main/videos/Los Herederos de Nuevo Leon - Nac\u00ed Para Quererla ( Audio Oficial )-x7orq2Gjls8.mp4"
        },
        {
            "id": "LWgIg7cZGho",
            "name": "Llegan Empujando-LWgIg7cZGho.mp4",
            "path": "/home/alanmatzumiya/Videos/container/l1/videos/Llegan Empujando-LWgIg7cZGho.mp4",
            "size": 2.463787,
            "url": "https://github.com/circuitalmynds/music_l1/raw/main/videos/Llegan Empujando-LWgIg7cZGho.mp4"
        },
        {
            "id": "H-B8CtlSbis",
            "name": "La Polla Records - Pitufar\u00e9-H-B8CtlSbis.mp4",
            "path": "/home/alanmatzumiya/Videos/container/l1/videos/La Polla Records - Pitufar\u00e9-H-B8CtlSbis.mp4",
            "size": 5.180823999999999,
            "url": "https://github.com/circuitalmynds/music_l1/raw/main/videos/La Polla Records - Pitufar\u00e9-H-B8CtlSbis.mp4"
        },
        {
            "id": "9NhaC0-ecWw",
            "name": "Leo Dan - Mary Es Mi Amor (En Vivo) ft. Andr\u00e9s Cepeda-9NhaC0-ecWw.mp4",
            "path": "/home/alanmatzumiya/Videos/container/l1/videos/Leo Dan - Mary Es Mi Amor (En Vivo) ft. Andr\u00e9s Cepeda-9NhaC0-ecWw.mp4",
            "size": 14.168184,
            "url": "https://github.com/circuitalmynds/music_l1/raw/main/videos/Leo Dan - Mary Es Mi Amor (En Vivo) ft. Andr\u00e9s Cepeda-9NhaC0-ecWw.mp4"
        },
        {
            "id": "OQ3-36nFXBI",
            "name": "La Barca Luis Miguel-OQ3-36nFXBI.mp4",
            "path": "/home/alanmatzumiya/Videos/container/l1/videos/La Barca Luis Miguel-OQ3-36nFXBI.mp4",
            "size": 10.86965,
            "url": "https://github.com/circuitalmynds/music_l1/raw/main/videos/La Barca Luis Miguel-OQ3-36nFXBI.mp4"
        },
        {
            "id": "HbeWjNFL8aY",
            "name": "Los Apson. Anoche me enamor\u00e9-HbeWjNFL8aY.mp4",
            "path": "/home/alanmatzumiya/Videos/container/l1/videos/Los Apson. Anoche me enamor\u00e9-HbeWjNFL8aY.mp4",
            "size": 13.568225,
            "url": "https://github.com/circuitalmynds/music_l1/raw/main/videos/Los Apson. Anoche me enamor\u00e9-HbeWjNFL8aY.mp4"
        },
        {
            "id": "4ajIFfSaEzE",
            "name": "Leeland - Follow You with special guest Brandon Heath (official video)-4ajIFfSaEzE.mp4",
            "path": "/home/alanmatzumiya/Videos/container/l1/videos/Leeland - Follow You with special guest Brandon Heath (official video)-4ajIFfSaEzE.mp4",
            "size": 24.757593,
            "url": "https://github.com/circuitalmynds/music_l1/raw/main/videos/Leeland - Follow You with special guest Brandon Heath (official video)-4ajIFfSaEzE.mp4"
        },
        {
            "id": "t7ZzXfqQN_I",
            "name": "Los Vega - No Llores mas-t7ZzXfqQN_I.mp4",
            "path": "/home/alanmatzumiya/Videos/container/l1/videos/Los Vega - No Llores mas-t7ZzXfqQN_I.mp4",
            "size": 6.112717,
            "url": "https://github.com/circuitalmynds/music_l1/raw/main/videos/Los Vega - No Llores mas-t7ZzXfqQN_I.mp4"
        },
        {
            "id": "IDywjc4Quh4",
            "name": "Limp Bizkit - Armpit - Lyrics-IDywjc4Quh4.mp4",
            "path": "/home/alanmatzumiya/Videos/container/l1/videos/Limp Bizkit - Armpit - Lyrics-IDywjc4Quh4.mp4",
            "size": 5.120134,
            "url": "https://github.com/circuitalmynds/music_l1/raw/main/videos/Limp Bizkit - Armpit - Lyrics-IDywjc4Quh4.mp4"
        },
        {
            "id": "L_eAVaZ2_LA",
            "name": "Los Herederos de Nuevo Le\u00f3n - Eslab\u00f3n por eslab\u00f3n [Live]-L_eAVaZ2_LA.mp4",
            "path": "/home/alanmatzumiya/Videos/container/l1/videos/Los Herederos de Nuevo Le\u00f3n - Eslab\u00f3n por eslab\u00f3n [Live]-L_eAVaZ2_LA.mp4",
            "size": 4.352455,
            "url": "https://github.com/circuitalmynds/music_l1/raw/main/videos/Los Herederos de Nuevo Le\u00f3n - Eslab\u00f3n por eslab\u00f3n [Live]-L_eAVaZ2_LA.mp4"
        },
        {
            "id": "akOe88HP980",
            "name": "Leonardo Favio - Ni el Clavel ni la Rosa-akOe88HP980.mp4",
            "path": "/home/alanmatzumiya/Videos/container/l1/videos/Leonardo Favio - Ni el Clavel ni la Rosa-akOe88HP980.mp4",
            "size": 9.402429999999999,
            "url": "https://github.com/circuitalmynds/music_l1/raw/main/videos/Leonardo Favio - Ni el Clavel ni la Rosa-akOe88HP980.mp4"
        },
        {
            "id": "VC3W7o7_ho4",
            "name": "Loss of innocence-VC3W7o7_ho4.mp4",
            "path": "/home/alanmatzumiya/Videos/container/l1/videos/Loss of innocence-VC3W7o7_ho4.mp4",
            "size": 2.299426,
            "url": "https://github.com/circuitalmynds/music_l1/raw/main/videos/Loss of innocence-VC3W7o7_ho4.mp4"
        },
        {
            "id": "RmsICVbs8Z4",
            "name": "Leo Dan - C\u00f3mo Te Extra\u00f1o Mi Amor (En Vivo) ft. Rub\u00e9n Albarr\u00e1n-RmsICVbs8Z4.mp4",
            "path": "/home/alanmatzumiya/Videos/container/l1/videos/Leo Dan - C\u00f3mo Te Extra\u00f1o Mi Amor (En Vivo) ft. Rub\u00e9n Albarr\u00e1n-RmsICVbs8Z4.mp4",
            "size": 15.110633,
            "url": "https://github.com/circuitalmynds/music_l1/raw/main/videos/Leo Dan - C\u00f3mo Te Extra\u00f1o Mi Amor (En Vivo) ft. Rub\u00e9n Albarr\u00e1n-RmsICVbs8Z4.mp4"
        },
        {
            "id": "nTGH0Hgc7_A",
            "name": "La Ley - Aqu\u00ed (Video Oficial)-nTGH0Hgc7_A.mp4",
            "path": "/home/alanmatzumiya/Videos/container/l1/videos/La Ley - Aqu\u00ed (Video Oficial)-nTGH0Hgc7_A.mp4",
            "size": 22.520198999999998,
            "url": "https://github.com/circuitalmynds/music_l1/raw/main/videos/La Ley - Aqu\u00ed (Video Oficial)-nTGH0Hgc7_A.mp4"
        },
        {
            "id": "pCDkx4Sfbkw",
            "name": "La Bonga-pCDkx4Sfbkw.mp4",
            "path": "/home/alanmatzumiya/Videos/container/l1/videos/La Bonga-pCDkx4Sfbkw.mp4",
            "size": 6.076394,
            "url": "https://github.com/circuitalmynds/music_l1/raw/main/videos/La Bonga-pCDkx4Sfbkw.mp4"
        },
        {
            "id": "eBrVepvVSfM",
            "name": "La Perra Vida - Todos Estamos Muertos  (Sessiones en Directo)-eBrVepvVSfM.mp4",
            "path": "/home/alanmatzumiya/Videos/container/l1/videos/La Perra Vida - Todos Estamos Muertos  (Sessiones en Directo)-eBrVepvVSfM.mp4",
            "size": 14.465340999999999,
            "url": "https://github.com/circuitalmynds/music_l1/raw/main/videos/La Perra Vida - Todos Estamos Muertos  (Sessiones en Directo)-eBrVepvVSfM.mp4"
        },
        {
            "id": "OeSAuLiwUOg",
            "name": "Lamento Borincano (En Vivo)-OeSAuLiwUOg.mp4",
            "path": "/home/alanmatzumiya/Videos/container/l1/videos/Lamento Borincano (En Vivo)-OeSAuLiwUOg.mp4",
            "size": 12.808845,
            "url": "https://github.com/circuitalmynds/music_l1/raw/main/videos/Lamento Borincano (En Vivo)-OeSAuLiwUOg.mp4"
        },
        {
            "id": "eis6ac9Ruhk",
            "name": "LOS CADETES DE LINARES CON UNA MANO EN LA FRENTE-eis6ac9Ruhk.mp4",
            "path": "/home/alanmatzumiya/Videos/container/l1/videos/LOS CADETES DE LINARES CON UNA MANO EN LA FRENTE-eis6ac9Ruhk.mp4",
            "size": 10.027994999999999,
            "url": "https://github.com/circuitalmynds/music_l1/raw/main/videos/LOS CADETES DE LINARES CON UNA MANO EN LA FRENTE-eis6ac9Ruhk.mp4"
        },
        {
            "id": "RGsM-nDfxQs",
            "name": "Let The Tears Begin ~ Johnny Bond (1963) (Country & Western)-RGsM-nDfxQs.mp4",
            "path": "/home/alanmatzumiya/Videos/container/l1/videos/Let The Tears Begin ~ Johnny Bond (1963) (Country & Western)-RGsM-nDfxQs.mp4",
            "size": 5.50672,
            "url": "https://github.com/circuitalmynds/music_l1/raw/main/videos/Let The Tears Begin ~ Johnny Bond (1963) (Country & Western)-RGsM-nDfxQs.mp4"
        },
        {
            "id": "LEg5mroggFc",
            "name": "Leonardo Favio - O Quiz\u00e1s Simplemente Le Regale una Rosa (Official Audio)-LEg5mroggFc.mp4",
            "path": "/home/alanmatzumiya/Videos/container/l1/videos/Leonardo Favio - O Quiz\u00e1s Simplemente Le Regale una Rosa (Official Audio)-LEg5mroggFc.mp4",
            "size": 3.6866999999999996,
            "url": "https://github.com/circuitalmynds/music_l1/raw/main/videos/Leonardo Favio - O Quiz\u00e1s Simplemente Le Regale una Rosa (Official Audio)-LEg5mroggFc.mp4"
        },
        {
            "id": "DnhigTO1Kj4",
            "name": "Los Herederos de Nuevo Leon - Tus Errores ( Audio Oficial )-DnhigTO1Kj4.mp4",
            "path": "/home/alanmatzumiya/Videos/container/l1/videos/Los Herederos de Nuevo Leon - Tus Errores ( Audio Oficial )-DnhigTO1Kj4.mp4",
            "size": 11.934284,
            "url": "https://github.com/circuitalmynds/music_l1/raw/main/videos/Los Herederos de Nuevo Leon - Tus Errores ( Audio Oficial )-DnhigTO1Kj4.mp4"
        },
        {
            "id": "xo3xBBZzRAk",
            "name": "London Grammar - How Does It Feel (Official Video)-xo3xBBZzRAk.mp4",
            "path": "/home/alanmatzumiya/Videos/container/l1/videos/London Grammar - How Does It Feel (Official Video)-xo3xBBZzRAk.mp4",
            "size": 11.924679,
            "url": "https://github.com/circuitalmynds/music_l1/raw/main/videos/London Grammar - How Does It Feel (Official Video)-xo3xBBZzRAk.mp4"
        },
        {
            "id": "1aSc2xjtn6M",
            "name": "Leo Dan - P\u00eddeme la Luna (En Vivo) ft. La Original Banda el Lim\u00f3n de Salvador Liz\u00e1rraga-1aSc2xjtn6M.mp4",
            "path": "/home/alanmatzumiya/Videos/container/l1/videos/Leo Dan - P\u00eddeme la Luna (En Vivo) ft. La Original Banda el Lim\u00f3n de Salvador Liz\u00e1rraga-1aSc2xjtn6M.mp4",
            "size": 20.757973,
            "url": "https://github.com/circuitalmynds/music_l1/raw/main/videos/Leo Dan - P\u00eddeme la Luna (En Vivo) ft. La Original Banda el Lim\u00f3n de Salvador Liz\u00e1rraga-1aSc2xjtn6M.mp4"
        },
        {
            "id": "XrNOoLiTMjE",
            "name": "La Polla Records - Ellos Dicen Mierda-XrNOoLiTMjE.mp4",
            "path": "/home/alanmatzumiya/Videos/container/l1/videos/La Polla Records - Ellos Dicen Mierda-XrNOoLiTMjE.mp4",
            "size": 6.354213,
            "url": "https://github.com/circuitalmynds/music_l1/raw/main/videos/La Polla Records - Ellos Dicen Mierda-XrNOoLiTMjE.mp4"
        },
        {
            "id": "TGL0w6Aq0Zk",
            "name": "Leo Dan - Siempre Estoy Pensando en Ella (En Vivo) ft. Luis Humberto Navejas-TGL0w6Aq0Zk.mp4",
            "path": "/home/alanmatzumiya/Videos/container/l1/videos/Leo Dan - Siempre Estoy Pensando en Ella (En Vivo) ft. Luis Humberto Navejas-TGL0w6Aq0Zk.mp4",
            "size": 14.149826,
            "url": "https://github.com/circuitalmynds/music_l1/raw/main/videos/Leo Dan - Siempre Estoy Pensando en Ella (En Vivo) ft. Luis Humberto Navejas-TGL0w6Aq0Zk.mp4"
        },
        {
            "id": "rq2GSkRwWeg",
            "name": "Los Invasores De Nuevo Leon - Con Tu Imagen-rq2GSkRwWeg.mp4",
            "path": "/home/alanmatzumiya/Videos/container/l1/videos/Los Invasores De Nuevo Leon - Con Tu Imagen-rq2GSkRwWeg.mp4",
            "size": 4.31273,
            "url": "https://github.com/circuitalmynds/music_l1/raw/main/videos/Los Invasores De Nuevo Leon - Con Tu Imagen-rq2GSkRwWeg.mp4"
        },
        {
            "id": "dLxfy3Z1d9k",
            "name": "Los Herederos de Nuevo Leon - No Se Debe ( Audio Oficial )-dLxfy3Z1d9k.mp4",
            "path": "/home/alanmatzumiya/Videos/container/l1/videos/Los Herederos de Nuevo Leon - No Se Debe ( Audio Oficial )-dLxfy3Z1d9k.mp4",
            "size": 7.145776,
            "url": "https://github.com/circuitalmynds/music_l1/raw/main/videos/Los Herederos de Nuevo Leon - No Se Debe ( Audio Oficial )-dLxfy3Z1d9k.mp4"
        },
        {
            "id": "V5aphiM0YVM",
            "name": "Liga Desorden - La Bruja-V5aphiM0YVM.mp4",
            "path": "/home/alanmatzumiya/Videos/container/l1/videos/Liga Desorden - La Bruja-V5aphiM0YVM.mp4",
            "size": 4.659077,
            "url": "https://github.com/circuitalmynds/music_l1/raw/main/videos/Liga Desorden - La Bruja-V5aphiM0YVM.mp4"
        },
        {
            "id": "U1Om8agaVIw",
            "name": "Los Herederos de Nuevo Le\u00f3n - Materia Dispuesta ( Audio Oficial )-U1Om8agaVIw.mp4",
            "path": "/home/alanmatzumiya/Videos/container/l1/videos/Los Herederos de Nuevo Le\u00f3n - Materia Dispuesta ( Audio Oficial )-U1Om8agaVIw.mp4",
            "size": 6.1816059999999995,
            "url": "https://github.com/circuitalmynds/music_l1/raw/main/videos/Los Herederos de Nuevo Le\u00f3n - Materia Dispuesta ( Audio Oficial )-U1Om8agaVIw.mp4"
        },
        {
            "id": "Z_fqwmPkW_Y",
            "name": "LOS HERMANOS VEGA - CONTIGO O SIN TI.wmv-Z_fqwmPkW_Y.mp4",
            "path": "/home/alanmatzumiya/Videos/container/l1/videos/LOS HERMANOS VEGA - CONTIGO O SIN TI.wmv-Z_fqwmPkW_Y.mp4",
            "size": 4.0843229999999995,
            "url": "https://github.com/circuitalmynds/music_l1/raw/main/videos/LOS HERMANOS VEGA - CONTIGO O SIN TI.wmv-Z_fqwmPkW_Y.mp4"
        },
        {
            "id": "L5iJn4OJH2o",
            "name": "Los Hermanos Vega El Burro Moro-L5iJn4OJH2o.mp4",
            "path": "/home/alanmatzumiya/Videos/container/l1/videos/Los Hermanos Vega El Burro Moro-L5iJn4OJH2o.mp4",
            "size": 4.655819999999999,
            "url": "https://github.com/circuitalmynds/music_l1/raw/main/videos/Los Hermanos Vega El Burro Moro-L5iJn4OJH2o.mp4"
        },
        {
            "id": "PKqh91MCaJI",
            "name": "Los Hermanos Vega El Caporal-PKqh91MCaJI.mp4",
            "path": "/home/alanmatzumiya/Videos/container/l1/videos/Los Hermanos Vega El Caporal-PKqh91MCaJI.mp4",
            "size": 5.726465999999999,
            "url": "https://github.com/circuitalmynds/music_l1/raw/main/videos/Los Hermanos Vega El Caporal-PKqh91MCaJI.mp4"
        },
        {
            "id": "Jt8dMLJAkw8",
            "name": "La Ni\u00f1a de Puerta Oscura-Jt8dMLJAkw8.mp4",
            "path": "/home/alanmatzumiya/Videos/container/l1/videos/La Ni\u00f1a de Puerta Oscura-Jt8dMLJAkw8.mp4",
            "size": 5.162782,
            "url": "https://github.com/circuitalmynds/music_l1/raw/main/videos/La Ni\u00f1a de Puerta Oscura-Jt8dMLJAkw8.mp4"
        },
        {
            "id": "ZpUYjpKg9KY",
            "name": "Limp Bizkit - Break Stuff (Official Music Video)-ZpUYjpKg9KY.mp4",
            "path": "/home/alanmatzumiya/Videos/container/l1/videos/Limp Bizkit - Break Stuff (Official Music Video)-ZpUYjpKg9KY.mp4",
            "size": 10.157145,
            "url": "https://github.com/circuitalmynds/music_l1/raw/main/videos/Limp Bizkit - Break Stuff (Official Music Video)-ZpUYjpKg9KY.mp4"
        },
        {
            "id": "Yh5qoezFApE",
            "name": "Los Hnos  Vega La Yegua Y La Potranca-Yh5qoezFApE.mp4",
            "path": "/home/alanmatzumiya/Videos/container/l1/videos/Los Hnos  Vega La Yegua Y La Potranca-Yh5qoezFApE.mp4",
            "size": 7.732199,
            "url": "https://github.com/circuitalmynds/music_l1/raw/main/videos/Los Hnos  Vega La Yegua Y La Potranca-Yh5qoezFApE.mp4"
        },
        {
            "id": "wf4qLmjVHV4",
            "name": "Los Valientes de Sonora-wf4qLmjVHV4.mp4",
            "path": "/home/alanmatzumiya/Videos/container/l1/videos/Los Valientes de Sonora-wf4qLmjVHV4.mp4",
            "size": 7.910729,
            "url": "https://github.com/circuitalmynds/music_l1/raw/main/videos/Los Valientes de Sonora-wf4qLmjVHV4.mp4"
        },
        {
            "id": "gasvf8BSm_o",
            "name": "Los Herederos de Nuevo Le\u00f3n - No Creas ( Audio Oficial )-gasvf8BSm_o.mp4",
            "path": "/home/alanmatzumiya/Videos/container/l1/videos/Los Herederos de Nuevo Le\u00f3n - No Creas ( Audio Oficial )-gasvf8BSm_o.mp4",
            "size": 6.8458369999999995,
            "url": "https://github.com/circuitalmynds/music_l1/raw/main/videos/Los Herederos de Nuevo Le\u00f3n - No Creas ( Audio Oficial )-gasvf8BSm_o.mp4"
        },
        {
            "id": "MXJEgrD3Jn8",
            "name": "Los Herederos de Nuevo Leon - Nuestros Herederos ( Audio Oficial )-MXJEgrD3Jn8.mp4",
            "path": "/home/alanmatzumiya/Videos/container/l1/videos/Los Herederos de Nuevo Leon - Nuestros Herederos ( Audio Oficial )-MXJEgrD3Jn8.mp4",
            "size": 12.114203,
            "url": "https://github.com/circuitalmynds/music_l1/raw/main/videos/Los Herederos de Nuevo Leon - Nuestros Herederos ( Audio Oficial )-MXJEgrD3Jn8.mp4"
        },
        {
            "id": "Y1pS_6hErDA",
            "name": "Lewis & Clark _ Tommy Emmanuel-Y1pS_6hErDA.mp4",
            "path": "/home/alanmatzumiya/Videos/container/l1/videos/Lewis & Clark _ Tommy Emmanuel-Y1pS_6hErDA.mp4",
            "size": 16.025786,
            "url": "https://github.com/circuitalmynds/music_l1/raw/main/videos/Lewis & Clark _ Tommy Emmanuel-Y1pS_6hErDA.mp4"
        },
        {
            "id": "7C8y7QJKgfI",
            "name": "la repera asto pituak-7C8y7QJKgfI.mp4",
            "path": "/home/alanmatzumiya/Videos/container/l1/videos/la repera asto pituak-7C8y7QJKgfI.mp4",
            "size": 5.9300489999999995,
            "url": "https://github.com/circuitalmynds/music_l1/raw/main/videos/la repera asto pituak-7C8y7QJKgfI.mp4"
        },
        {
            "id": "eV76VDDKriY",
            "name": "Thalberg - Moses Fantasy-eV76VDDKriY.mp4",
            "path": "/home/alanmatzumiya/Videos/container/l1/videos/Thalberg - Moses Fantasy-eV76VDDKriY.mp4",
            "size": 34.571715999999995,
            "url": "https://github.com/circuitalmynds/music_l1/raw/main/videos/Thalberg - Moses Fantasy-eV76VDDKriY.mp4"
        },
        {
            "id": "YInIz_TPD0Y",
            "name": "LA MINI MINI (AUDIO ORIGINAL) - \ud83d\udd25LA CONCENTRACION\ud83d\udd25 #LACONCECUMBIAS-YInIz_TPD0Y.mp4",
            "path": "/home/alanmatzumiya/Videos/container/l1/videos/LA MINI MINI (AUDIO ORIGINAL) - \ud83d\udd25LA CONCENTRACION\ud83d\udd25 #LACONCECUMBIAS-YInIz_TPD0Y.mp4",
            "size": 6.170788,
            "url": "https://github.com/circuitalmynds/music_l1/raw/main/videos/LA MINI MINI (AUDIO ORIGINAL) - \ud83d\udd25LA CONCENTRACION\ud83d\udd25 #LACONCECUMBIAS-YInIz_TPD0Y.mp4"
        },
        {
            "id": "FcH_BEQPzSk",
            "name": "LA SANTA GRIFA (YUSAK) FT. ELIE TIGRE _ NO VALE LA PENA _ VIDEO OFICIAL (Prod. FiiKs Beats)-FcH_BEQPzSk.mp4",
            "path": "/home/alanmatzumiya/Videos/container/l1/videos/LA SANTA GRIFA (YUSAK) FT. ELIE TIGRE _ NO VALE LA PENA _ VIDEO OFICIAL (Prod. FiiKs Beats)-FcH_BEQPzSk.mp4",
            "size": 10.801368,
            "url": "https://github.com/circuitalmynds/music_l1/raw/main/videos/LA SANTA GRIFA (YUSAK) FT. ELIE TIGRE _ NO VALE LA PENA _ VIDEO OFICIAL (Prod. FiiKs Beats)-FcH_BEQPzSk.mp4"
        },
        {
            "id": "W6Tuj1aTHn0",
            "name": "Las Tres Tumbas-W6Tuj1aTHn0.mp4",
            "path": "/home/alanmatzumiya/Videos/container/l1/videos/Las Tres Tumbas-W6Tuj1aTHn0.mp4",
            "size": 5.278519999999999,
            "url": "https://github.com/circuitalmynds/music_l1/raw/main/videos/Las Tres Tumbas-W6Tuj1aTHn0.mp4"
        },
        {
            "id": "H7y_Gg7J9sw",
            "name": "la coyota-mil cervezas-H7y_Gg7J9sw.mp4",
            "path": "/home/alanmatzumiya/Videos/container/l1/videos/la coyota-mil cervezas-H7y_Gg7J9sw.mp4",
            "size": 2.663382,
            "url": "https://github.com/circuitalmynds/music_l1/raw/main/videos/la coyota-mil cervezas-H7y_Gg7J9sw.mp4"
        },
        {
            "id": "uaLjnA7uBFg",
            "name": "Llegar\u00e1s por los calveros-uaLjnA7uBFg.mp4",
            "path": "/home/alanmatzumiya/Videos/container/l1/videos/Llegar\u00e1s por los calveros-uaLjnA7uBFg.mp4",
            "size": 0.891666,
            "url": "https://github.com/circuitalmynds/music_l1/raw/main/videos/Llegar\u00e1s por los calveros-uaLjnA7uBFg.mp4"
        },
        {
            "id": "PgEGjcrw3n8",
            "name": "LA MUCURA (AUDIO ORIGINAL) - \ud83d\udd25LA CONCENTRACION \ud83d\udd25-PgEGjcrw3n8.mp4",
            "path": "/home/alanmatzumiya/Videos/container/l1/videos/LA MUCURA (AUDIO ORIGINAL) - \ud83d\udd25LA CONCENTRACION \ud83d\udd25-PgEGjcrw3n8.mp4",
            "size": 7.514990999999999,
            "url": "https://github.com/circuitalmynds/music_l1/raw/main/videos/LA MUCURA (AUDIO ORIGINAL) - \ud83d\udd25LA CONCENTRACION \ud83d\udd25-PgEGjcrw3n8.mp4"
        },
        {
            "id": "lKNSPtbQ7mA",
            "name": "La Novia De Mi Hermano-lKNSPtbQ7mA.mp4",
            "path": "/home/alanmatzumiya/Videos/container/l1/videos/La Novia De Mi Hermano-lKNSPtbQ7mA.mp4",
            "size": 6.656051,
            "url": "https://github.com/circuitalmynds/music_l1/raw/main/videos/La Novia De Mi Hermano-lKNSPtbQ7mA.mp4"
        },
        {
            "id": "od880vDGSOU",
            "name": "lepoan hartu ta segi aurrera traducido-od880vDGSOU.mp4",
            "path": "/home/alanmatzumiya/Videos/container/l1/videos/lepoan hartu ta segi aurrera traducido-od880vDGSOU.mp4",
            "size": 6.4884319999999995,
            "url": "https://github.com/circuitalmynds/music_l1/raw/main/videos/lepoan hartu ta segi aurrera traducido-od880vDGSOU.mp4"
        },
        {
            "id": "dqkD0qhAmTs",
            "name": "La Hormiguita - La Coyota-dqkD0qhAmTs.mp4",
            "path": "/home/alanmatzumiya/Videos/container/l1/videos/La Hormiguita - La Coyota-dqkD0qhAmTs.mp4",
            "size": 5.041021,
            "url": "https://github.com/circuitalmynds/music_l1/raw/main/videos/La Hormiguita - La Coyota-dqkD0qhAmTs.mp4"
        },
        {
            "id": "DUbPAmtFzGw",
            "name": "Los Cadetes de Linares - El Muchacho y El Potro-DUbPAmtFzGw.mp4",
            "path": "/home/alanmatzumiya/Videos/container/l1/videos/Los Cadetes de Linares - El Muchacho y El Potro-DUbPAmtFzGw.mp4",
            "size": 6.186548,
            "url": "https://github.com/circuitalmynds/music_l1/raw/main/videos/Los Cadetes de Linares - El Muchacho y El Potro-DUbPAmtFzGw.mp4"
        },
        {
            "id": "JlH5NPj6LXU",
            "name": "Los Intocables -  No Hay Futuro-JlH5NPj6LXU.mp4",
            "path": "/home/alanmatzumiya/Videos/container/l1/videos/Los Intocables -  No Hay Futuro-JlH5NPj6LXU.mp4",
            "size": 11.469536999999999,
            "url": "https://github.com/circuitalmynds/music_l1/raw/main/videos/Los Intocables -  No Hay Futuro-JlH5NPj6LXU.mp4"
        },
        {
            "id": "4_dLk3Fjkf8",
            "name": "LOS HERMANOS VEGA - CARCEL DE GUADALAJARA.wmv-4_dLk3Fjkf8.mp4",
            "path": "/home/alanmatzumiya/Videos/container/l1/videos/LOS HERMANOS VEGA - CARCEL DE GUADALAJARA.wmv-4_dLk3Fjkf8.mp4",
            "size": 5.9209689999999995,
            "url": "https://github.com/circuitalmynds/music_l1/raw/main/videos/LOS HERMANOS VEGA - CARCEL DE GUADALAJARA.wmv-4_dLk3Fjkf8.mp4"
        },
        {
            "id": "iaww13roH_w",
            "name": "Los Invasores De Nuevo Le\u00f3n - Cuando Llora Un Hombre-iaww13roH_w.mp4",
            "path": "/home/alanmatzumiya/Videos/container/l1/videos/Los Invasores De Nuevo Le\u00f3n - Cuando Llora Un Hombre-iaww13roH_w.mp4",
            "size": 3.6717999999999997,
            "url": "https://github.com/circuitalmynds/music_l1/raw/main/videos/Los Invasores De Nuevo Le\u00f3n - Cuando Llora Un Hombre-iaww13roH_w.mp4"
        },
        {
            "id": "ylOU1GyXDjo",
            "name": "Liberaci\u00f3n - Enamorado De Un Fantasma (Chyron)-ylOU1GyXDjo.mp4",
            "path": "/home/alanmatzumiya/Videos/container/l1/videos/Liberaci\u00f3n - Enamorado De Un Fantasma (Chyron)-ylOU1GyXDjo.mp4",
            "size": 18.772299999999998,
            "url": "https://github.com/circuitalmynds/music_l1/raw/main/videos/Liberaci\u00f3n - Enamorado De Un Fantasma (Chyron)-ylOU1GyXDjo.mp4"
        },
        {
            "id": "MYt_jSVNDq4",
            "name": "Los Tres - C\u00e1rcel, Hospital & Cementerio-MYt_jSVNDq4.mp4",
            "path": "/home/alanmatzumiya/Videos/container/l1/videos/Los Tres - C\u00e1rcel, Hospital & Cementerio-MYt_jSVNDq4.mp4",
            "size": 5.7512039999999995,
            "url": "https://github.com/circuitalmynds/music_l1/raw/main/videos/Los Tres - C\u00e1rcel, Hospital & Cementerio-MYt_jSVNDq4.mp4"
        },
        {
            "id": "1Sj-FOu0blY",
            "name": "Listen To The Wind ~ Jeanie Johnson (1958)-1Sj-FOu0blY.mp4",
            "path": "/home/alanmatzumiya/Videos/container/l1/videos/Listen To The Wind ~ Jeanie Johnson (1958)-1Sj-FOu0blY.mp4",
            "size": 6.4750879999999995,
            "url": "https://github.com/circuitalmynds/music_l1/raw/main/videos/Listen To The Wind ~ Jeanie Johnson (1958)-1Sj-FOu0blY.mp4"
        },
        {
            "id": "AH-ByzEkaJI",
            "name": "liberacion animal estigia-AH-ByzEkaJI.mp4",
            "path": "/home/alanmatzumiya/Videos/container/l1/videos/liberacion animal estigia-AH-ByzEkaJI.mp4",
            "size": 5.0083009999999994,
            "url": "https://github.com/circuitalmynds/music_l1/raw/main/videos/liberacion animal estigia-AH-ByzEkaJI.mp4"
        },
        {
            "id": "uETlS67gJ68",
            "name": "Loathe-uETlS67gJ68.mp4",
            "path": "/home/alanmatzumiya/Videos/container/l1/videos/Loathe-uETlS67gJ68.mp4",
            "size": 9.518744,
            "url": "https://github.com/circuitalmynds/music_l1/raw/main/videos/Loathe-uETlS67gJ68.mp4"
        },
        {
            "id": "e3ciRgl8wcM",
            "name": "Laurel Aitken & The Skatalites - Mood for Ska-e3ciRgl8wcM.mp4",
            "path": "/home/alanmatzumiya/Videos/container/l1/videos/Laurel Aitken & The Skatalites - Mood for Ska-e3ciRgl8wcM.mp4",
            "size": 6.26075,
            "url": "https://github.com/circuitalmynds/music_l1/raw/main/videos/Laurel Aitken & The Skatalites - Mood for Ska-e3ciRgl8wcM.mp4"
        },
        {
            "id": "g4umYs6Hmmc",
            "name": "Los Muertos de Cristo - L\u00e1grimas de Sangre [LETRA]-g4umYs6Hmmc.mp4",
            "path": "/home/alanmatzumiya/Videos/container/l1/videos/Los Muertos de Cristo - L\u00e1grimas de Sangre [LETRA]-g4umYs6Hmmc.mp4",
            "size": 7.118271999999999,
            "url": "https://github.com/circuitalmynds/music_l1/raw/main/videos/Los Muertos de Cristo - L\u00e1grimas de Sangre [LETRA]-g4umYs6Hmmc.mp4"
        }
    ],
    "total_size": 955.4905159999998
}